alibabacloud_vpc20160428/__init__.py
alibabacloud_vpc20160428/client.py
alibabacloud_vpc20160428/models/__init__.py
alibabacloud_vpc20160428/models/_activate_router_interface_request.py
alibabacloud_vpc20160428/models/_activate_router_interface_response.py
alibabacloud_vpc20160428/models/_activate_router_interface_response_body.py
alibabacloud_vpc20160428/models/_active_flow_log_request.py
alibabacloud_vpc20160428/models/_active_flow_log_response.py
alibabacloud_vpc20160428/models/_active_flow_log_response_body.py
alibabacloud_vpc20160428/models/_add_bgp_network_request.py
alibabacloud_vpc20160428/models/_add_bgp_network_response.py
alibabacloud_vpc20160428/models/_add_bgp_network_response_body.py
alibabacloud_vpc20160428/models/_add_common_bandwidth_package_ip_request.py
alibabacloud_vpc20160428/models/_add_common_bandwidth_package_ip_response.py
alibabacloud_vpc20160428/models/_add_common_bandwidth_package_ip_response_body.py
alibabacloud_vpc20160428/models/_add_common_bandwidth_package_ips_request.py
alibabacloud_vpc20160428/models/_add_common_bandwidth_package_ips_response.py
alibabacloud_vpc20160428/models/_add_common_bandwidth_package_ips_response_body.py
alibabacloud_vpc20160428/models/_add_global_acceleration_instance_ip_request.py
alibabacloud_vpc20160428/models/_add_global_acceleration_instance_ip_response.py
alibabacloud_vpc20160428/models/_add_global_acceleration_instance_ip_response_body.py
alibabacloud_vpc20160428/models/_add_ipv_6translator_acl_list_entry_request.py
alibabacloud_vpc20160428/models/_add_ipv_6translator_acl_list_entry_response.py
alibabacloud_vpc20160428/models/_add_ipv_6translator_acl_list_entry_response_body.py
alibabacloud_vpc20160428/models/_add_public_ip_address_pool_cidr_block_request.py
alibabacloud_vpc20160428/models/_add_public_ip_address_pool_cidr_block_response.py
alibabacloud_vpc20160428/models/_add_public_ip_address_pool_cidr_block_response_body.py
alibabacloud_vpc20160428-6.15.0.dist-info/LICENSE
alibabacloud_vpc20160428-6.15.0.dist-info/METADATA
alibabacloud_vpc20160428-6.15.0.dist-info/WHEEL
alibabacloud_vpc20160428-6.15.0.dist-info/top_level.txt
alibabacloud_vpc20160428-6.15.0.dist-info/RECORD
